aiochat/__init__.py
aiochat/agent.py
aiochat/channel.py
aiochat/engine.py
aiochat/helpers.py
aiochat-0.0.3.dist-info/LICENCE
aiochat-0.0.3.dist-info/METADATA
aiochat-0.0.3.dist-info/WHEEL
aiochat-0.0.3.dist-info/top_level.txt
aiochat-0.0.3.dist-info/RECORD
