Metadata-Version: 2.1
Name: aiochat
Version: 0.0.3
Summary: Simple RPC server/client framework.
Home-page: https://github.com/Exahilosys/aiochat
Author: Exahilosys
License: MIT
Platform: UNKNOWN
